{
  "templates": {
    "default": {
      "name": "標準テンプレート",
      "base_prompt": "商品タイトル: {title}\n\n{instruction}{brand_instruction}\n\n【絶対に守る制約】:\n1. 商品タイトルに実際に書かれている単語のみを使用してください\n2. 新しい単語、類義語、説明文を一切生成しないでください\n3. タイトルをスペース、カンマ、スラッシュ、括弧で分割した結果の単語から選んでください\n4. 「です」「ます」「について」などの説明は絶対に書かないでください\n5. 単語以外の文章や説明を出力することは禁止です\n\n出力形式: キーワードのみをカンマ区切りで返してください\n正しい例: RDX, ダブルエンド, パンチング, バッグ\n間違った例: WF4が制造されたキーワードです。",
      "instructions": {
        "strict": "この商品とほぼ同じものを探すためのキーワードを4～6個程度抽出してください。ブランド、商品の種類、主要な特徴などバランスよく選んでください。",
        "moderate": "類似商品を探すためのキーワードを3～4個抽出してください。大まかなカテゴリや商品ジャンルを中心に選んでください。",
        "loose": "関連商品を非常に幅広く探すためのキーワードを2～3個だけ抽出してください。最も大きなカテゴリ（テレビ、スマホ、バッグなど）のみを選んでください。細かい型番や特徴は含めないでください。"
      }
    },
    "simple": {
      "name": "シンプル版",
      "base_prompt": "商品タイトル: {title}\n\n{instruction}{brand_instruction}\n\nタイトル内の単語からキーワードを選んでカンマ区切りで返してください。",
      "instructions": {
        "strict": "同一商品検索用キーワードを抽出",
        "moderate": "類似商品検索用キーワードを抽出",
        "loose": "関連商品検索用キーワードを抽出"
      }
    }
  },
  "current_template": "default"
}